recourse/__init__.py
recourse/action_set.py
recourse/auditor.py
recourse/builder.py
recourse/cplex_helper.py
recourse/defaults.py
recourse/flipset.py
recourse/helper_functions.py
recourse/paths.py
recourse/print_recourse_audit_report.py
tests/__init__.py
tests/conftest.py
tests/test_action_set.py
tests/test_auditor.py
tests/test_bounds.py
tests/test_builder.py
tests/test_flipset.py
tests/test_solvers.py
recourse-1.0.0.dist-info/LICENSE
recourse-1.0.0.dist-info/METADATA
recourse-1.0.0.dist-info/WHEEL
recourse-1.0.0.dist-info/top_level.txt
recourse-1.0.0.dist-info/RECORD
