Metadata-Version: 2.1
Name: recourse
Version: 1.0.0
Summary: actionable-recourse is a python library for recourse verification and reporting.
Home-page: https://github.com/ustunb/actionable-recourse
Author: Berk Ustun, Alexander Spangher
Author-email: squall14414@gmail.com, alexander.spangher@gmail.com
License: UNKNOWN
Platform: UNKNOWN
Requires-Python: >=3.6
Requires-Dist: numpy (>=1.14.0)
Requires-Dist: scipy (>=0.19.1)
Requires-Dist: scikit-learn (>=0.19.1)
Requires-Dist: pandas (>=0.23.4)
Requires-Dist: cplex (>=12.8)
Requires-Dist: mip (==1.12.0)
Requires-Dist: prettytable (>=0.7.2)
Requires-Dist: matplotlib (>=3.0.2)
Requires-Dist: seaborn (>=0.9.0)
Requires-Dist: traitlets (>=4.3.2)
Requires-Dist: IPython (>=7.2.0)
Requires-Dist: pytest (>=4.3.0)
Requires-Dist: tqdm (>=4.24.0)
Requires-Dist: jinja2 (>=2.10.1)
